{
  "name": "wvocabulary",
  "version": "0.3.302",
  "description": "Vocabulary of phrases, primarily for CLI.",
  "author": "Kostiantyn Wandalen <wandalen@obox.systems>",
  "license": "MIT",
  "main": "proto/node_modules/wvocabulary",
  "files": [
    "proto/wtools/amid/l1/vocabulary",
    "out",
    "proto/node_modules",
    "proto/node_modules/Tools",
    "proto/node_modules/wvocabulary"
  ],
  "scripts": {
    "test": "wtest .run 'proto/**' rapidity:-3",
    "docgen": "wdocgen proto"
  },
  "repository": {
    "type": "git",
    "url": "https://github.com/Wandalen/wVocabulary.git"
  },
  "bugs": {
    "url": "https://github.com/Wandalen/wVocabulary/issues"
  },
  "dependencies": {
    "wTools": "",
    "wstringsextra": "",
    "wstringer": "",
    "wCopyable": ""
  },
  "devDependencies": {
    "wTesting": "",
    "eslint": "7.32.0"
  },
  "keywords": [
    "wTools",
    "vocabulary",
    "partial match",
    "phrase",
    "subphrase",
    "words",
    "CUI",
    "CLI",
    "user interface",
    "commands"
  ]
}
